{"state":"NV","stateName":"Nevada","source":"CDC PLACES","sourceLong":"CDC PLACES: Local Data for Better Health (model-based estimates)","datasetCounty":"i46a-9kgh","datasetPlace":"eav7-hnsx","sourceYear":2023,"fetchedAt":"2026-06-16","minPlacePopulation":1000,"countyCount":17,"placeCount":62,"counties":[{"name":"Nye","fips":"32023","rate":39.7,"ci":"(32.7, 47.3)","rank":1},{"name":"Eureka","fips":"32011","rate":38.8,"ci":"(29.6, 48.8)","rank":2},{"name":"Mineral","fips":"32021","rate":38.2,"ci":"(29.1, 47.5)","rank":3},{"name":"Elko","fips":"32007","rate":38.0,"ci":"(31.6, 45.1)","rank":4},{"name":"Churchill","fips":"32001","rate":37.8,"ci":"(29.7, 45.8)","rank":5},{"name":"Humboldt","fips":"32013","rate":36.2,"ci":"(28.2, 44.6)","rank":6},{"name":"Esmeralda","fips":"32009","rate":36.1,"ci":"(27.4, 45.6)","rank":7},{"name":"Pershing","fips":"32027","rate":35.7,"ci":"(27.3, 44.7)","rank":8},{"name":"Lyon","fips":"32019","rate":35.2,"ci":"(27.5, 43.0)","rank":9},{"name":"Lander","fips":"32015","rate":35.1,"ci":"(26.7, 44.1)","rank":10},{"name":"White Pine","fips":"32033","rate":34.4,"ci":"(26.6, 43.1)","rank":11},{"name":"Carson City","fips":"32510","rate":33.1,"ci":"(26.3, 40.2)","rank":12},{"name":"Storey","fips":"32029","rate":31.6,"ci":"(23.8, 40.6)","rank":13},{"name":"Lincoln","fips":"32017","rate":31.6,"ci":"(23.4, 40.3)","rank":14},{"name":"Clark","fips":"32003","rate":31.4,"ci":"(26.5, 36.5)","rank":15},{"name":"Washoe","fips":"32031","rate":28.5,"ci":"(23.9, 33.6)","rank":16},{"name":"Douglas","fips":"32005","rate":27.1,"ci":"(21.1, 34.0)","rank":17}],"places":[{"name":"Tonopah","fips":"3273600","rate":44.7,"population":2179,"lo":36.7,"hi":52.5,"rank":1},{"name":"Amargosa Valley","fips":"3201000","rate":43.5,"population":1064,"lo":35.7,"hi":51.7,"rank":2},{"name":"Owyhee","fips":"3253600","rate":42.2,"population":1027,"lo":34.8,"hi":49.6,"rank":3},{"name":"West Wendover","fips":"3283730","rate":41.5,"population":4512,"lo":34.1,"hi":48.9,"rank":4},{"name":"Wells","fips":"3283000","rate":39.9,"population":1237,"lo":32.5,"hi":47.6,"rank":5},{"name":"Yerington","fips":"3285400","rate":39.7,"population":3121,"lo":32.8,"hi":47.1,"rank":6},{"name":"Pahrump","fips":"3253800","rate":39.5,"population":44738,"lo":32.2,"hi":47.0,"rank":7},{"name":"Silver Springs","fips":"3267200","rate":37.9,"population":5629,"lo":31.1,"hi":45.2,"rank":8},{"name":"Hawthorne","fips":"3231300","rate":37.6,"population":3118,"lo":29.2,"hi":46.9,"rank":9},{"name":"Elko","fips":"3222500","rate":37.5,"population":20564,"lo":30.4,"hi":44.9,"rank":10},{"name":"Fallon","fips":"3224100","rate":37.4,"population":9327,"lo":29.8,"hi":45.2,"rank":11},{"name":"Stagecoach","fips":"3268800","rate":37.0,"population":2022,"lo":30.1,"hi":44.3,"rank":12},{"name":"Spring Creek","fips":"3268550","rate":36.9,"population":14967,"lo":30.0,"hi":44.1,"rank":13},{"name":"Carlin","fips":"3208900","rate":36.9,"population":2050,"lo":29.8,"hi":44.1,"rank":14},{"name":"Battle Mountain","fips":"3204900","rate":36.8,"population":3705,"lo":28.3,"hi":45.8,"rank":15},{"name":"Sunrise Manor","fips":"3271400","rate":36.2,"population":205618,"lo":31.2,"hi":41.5,"rank":16},{"name":"Winchester","fips":"3284600","rate":36.1,"population":36403,"lo":31.1,"hi":41.2,"rank":17},{"name":"Winnemucca","fips":"3284800","rate":36.0,"population":8431,"lo":28.1,"hi":44.5,"rank":18},{"name":"McGill","fips":"3244200","rate":35.8,"population":1010,"lo":27.9,"hi":44.5,"rank":19},{"name":"Smith Valley","fips":"3268050","rate":35.7,"population":1710,"lo":29.1,"hi":42.8,"rank":20},{"name":"Lovelock","fips":"3243000","rate":35.4,"population":1805,"lo":27.3,"hi":44.2,"rank":21},{"name":"Fernley","fips":"3224900","rate":35.0,"population":22895,"lo":28.3,"hi":42.2,"rank":22},{"name":"Moapa Town","fips":"3247840","rate":34.5,"population":1006,"lo":29.5,"hi":39.6,"rank":23},{"name":"North Las Vegas","fips":"3251800","rate":33.8,"population":262527,"lo":28.9,"hi":38.9,"rank":24},{"name":"Ely","fips":"3223500","rate":33.8,"population":3924,"lo":26.0,"hi":42.2,"rank":25},{"name":"Laughlin","fips":"3241000","rate":33.3,"population":8658,"lo":28.4,"hi":38.4,"rank":26},{"name":"Sun Valley","fips":"3271600","rate":33.2,"population":21178,"lo":28.2,"hi":38.3,"rank":27},{"name":"Paradise","fips":"3254600","rate":33.2,"population":191238,"lo":28.4,"hi":38.2,"rank":28},{"name":"Carson City","fips":"3209700","rate":33.1,"population":58639,"lo":26.7,"hi":40.4,"rank":29},{"name":"Whitney","fips":"3283800","rate":33.0,"population":49061,"lo":28.3,"hi":38.1,"rank":30},{"name":"Dayton","fips":"3217500","rate":32.9,"population":15153,"lo":26.5,"hi":39.9,"rank":31},{"name":"Nellis AFB","fips":"3250400","rate":32.8,"population":4379,"lo":28.1,"hi":37.9,"rank":32},{"name":"Las Vegas","fips":"3240000","rate":32.4,"population":641903,"lo":27.6,"hi":37.3,"rank":33},{"name":"Sandy Valley","fips":"3264600","rate":31.0,"population":1663,"lo":26.3,"hi":36.0,"rank":34},{"name":"Topaz Ranch Estates","fips":"3274400","rate":30.4,"population":1630,"lo":23.9,"hi":37.6,"rank":35},{"name":"Moapa Valley","fips":"3247880","rate":30.0,"population":6289,"lo":25.2,"hi":34.8,"rank":36},{"name":"Cold Springs","fips":"3214090","rate":29.8,"population":10153,"lo":25.2,"hi":34.9,"rank":37},{"name":"Mesquite","fips":"3246000","rate":29.5,"population":20471,"lo":25.0,"hi":34.2,"rank":38},{"name":"Bunkerville","fips":"3208100","rate":29.5,"population":1069,"lo":24.8,"hi":34.4,"rank":39},{"name":"Spring Valley","fips":"3268585","rate":29.3,"population":215597,"lo":24.9,"hi":34.0,"rank":40},{"name":"Lemmon Valley","fips":"3241800","rate":29.2,"population":4987,"lo":24.5,"hi":34.2,"rank":41},{"name":"Boulder City","fips":"3206500","rate":29.1,"population":14885,"lo":24.6,"hi":33.8,"rank":42},{"name":"Henderson","fips":"3231900","rate":28.9,"population":317610,"lo":24.4,"hi":33.6,"rank":43},{"name":"Sparks","fips":"3268400","rate":28.6,"population":108445,"lo":24.2,"hi":33.4,"rank":44},{"name":"Washoe Valley","fips":"3282250","rate":28.4,"population":3074,"lo":23.9,"hi":33.3,"rank":45},{"name":"Reno","fips":"3260600","rate":28.4,"population":264165,"lo":24.0,"hi":33.1,"rank":46},{"name":"Gardnerville Ranchos","fips":"3226500","rate":28.2,"population":11318,"lo":21.9,"hi":34.9,"rank":47},{"name":"Gardnerville","fips":"3226300","rate":28.1,"population":6211,"lo":21.6,"hi":35.2,"rank":48},{"name":"Enterprise","fips":"3223770","rate":27.8,"population":221831,"lo":23.5,"hi":32.4,"rank":49},{"name":"Verdi","fips":"3279400","rate":27.7,"population":1396,"lo":23.2,"hi":32.8,"rank":50},{"name":"Indian Hills","fips":"3235275","rate":27.6,"population":5962,"lo":21.5,"hi":34.5,"rank":51},{"name":"Spanish Springs","fips":"3268350","rate":27.5,"population":17314,"lo":23.0,"hi":32.2,"rank":52},{"name":"Golden Valley","fips":"3228860","rate":27.5,"population":1580,"lo":23.0,"hi":32.2,"rank":53},{"name":"East Valley","fips":"3221520","rate":27.1,"population":1558,"lo":20.8,"hi":34.3,"rank":54},{"name":"Minden","fips":"3247000","rate":27.0,"population":3442,"lo":20.9,"hi":34.1,"rank":55},{"name":"Ruhenstroth","fips":"3263450","rate":26.7,"population":1239,"lo":20.5,"hi":33.7,"rank":56},{"name":"Johnson Lane","fips":"3237190","rate":26.7,"population":6409,"lo":20.5,"hi":33.5,"rank":57},{"name":"Kingsbury","fips":"3238000","rate":26.5,"population":2313,"lo":20.2,"hi":33.5,"rank":58},{"name":"Mogul","fips":"3248000","rate":26.3,"population":1258,"lo":21.9,"hi":30.9,"rank":59},{"name":"Summerlin South","fips":"3270900","rate":26.1,"population":30744,"lo":21.9,"hi":30.7,"rank":60},{"name":"Incline Village","fips":"3235100","rate":25.6,"population":9462,"lo":21.4,"hi":30.2,"rank":61},{"name":"Genoa","fips":"3227100","rate":24.3,"population":1343,"lo":18.6,"hi":30.8,"rank":62}]}